ugly_todo/__init__.py
ugly_todo/__main__.py
ugly_todo/cli.py
ugly_todo/utd.py
ugly_todo/util.py
utd-0.1.3.dist-info/LICENSE
utd-0.1.3.dist-info/METADATA
utd-0.1.3.dist-info/WHEEL
utd-0.1.3.dist-info/entry_points.txt
utd-0.1.3.dist-info/top_level.txt
utd-0.1.3.dist-info/RECORD
