Metadata-Version: 2.1
Name: utd
Version: 0.1.3
Summary: Just an Ugly To-Do app that I wanted to develop.
Home-page: https://github.com/Murzchnvok/ugly-todo
Author: Murzchnvok
Author-email: murzchnvok@gmail.com
License: UNKNOWN
Project-URL: Bug Tracker, https://github.com/Murzchnvok/ugly-todo/issues
Keywords: "to-do note kanban-board minimalist"
Platform: UNKNOWN
Classifier: Environment :: Console
Classifier: License :: OSI Approved :: The Unlicense (Unlicense)
Classifier: Operating System :: MacOS
Classifier: Operating System :: Microsoft :: Windows
Classifier: Operating System :: POSIX
Classifier: Programming Language :: Python :: 3 :: Only
Requires-Python: >=3.10
License-File: LICENSE
Requires-Dist: colored (>=1.4.3)
